jaxfss/__init__.py
jaxfss/data.py
jaxfss/model.py
jaxfss/train.py
jaxfss-0.1.0.dist-info/LICENSE
jaxfss-0.1.0.dist-info/METADATA
jaxfss-0.1.0.dist-info/WHEEL
jaxfss-0.1.0.dist-info/top_level.txt
jaxfss-0.1.0.dist-info/RECORD
