Metadata-Version: 2.1
Name: jaxfss
Version: 0.1.0
Summary: JAX/Flax implementation of finite-size scaling
Home-page: https://github.com/yonesuke/jaxfss
Author: yonesuke
Author-email: 13e.e.c.13@gmail.com
Classifier: Programming Language :: Python :: 3
Classifier: License :: OSI Approved :: MIT License
Classifier: Operating System :: OS Independent
Requires-Python: >=3.7
License-File: LICENSE
Requires-Dist: jax
Requires-Dist: flax
Requires-Dist: optax
Requires-Dist: distrax
Requires-Dist: rationalnets
Requires-Dist: softclip
